{"execution_id": "sq4_20260107_182855_MV4_TOKIO_MARINE_COMPREHENSIVE", "session_id": "sess_20260107_182821", "session_name": "sq4", "category": "MV4", "product_id": "TOKIO_MARINE", "plan_id": "COMPREHENSIVE", "target_environment": "QA", "status": "completed", "timestamp": "2026-01-07T18:28:55.579579", "api_calls": [{"call_id": "call_sq4_20260107_182855_MV4_TOKIO_MARINE_COMPREHENSIVE_application_submit_qa", "execution_id": "sq4_20260107_182855_MV4_TOKIO_MARINE_COMPREHENSIVE", "tab_id": "sq4_20260107_182855_MV4_TOKIO_MARINE_COMPREHENSIVE", "api_step": "application_submit", "environment": "QA", "endpoint": "/api/v1/application-submit", "request_payload": {"category": "TOKIO", "product_id": "MARINE", "plan_id": "COMPREHENSIVE", "customer_data": {"customer_name": "John Doe", "customer_email": "john.doe@example.com", "customer_phone": "+60123456789", "date_of_birth": "1990-01-01", "address": {"street": "123 Main Street", "city": "Kuala Lumpur", "state": "Selangor", "postal_code": "50000", "country": "Malaysia"}}, "policy_start_date": "2026-02-01", "policy_end_date": "2027-01-31", "sum_insured": 50000, "application_date": "2026-01-07T18:28:55.988599"}, "response_data": {"status": "success", "application_id": "app_b737fe7ca6be", "category": "TOKIO", "product_id": "MARINE", "plan_id": "COMPREHENSIVE", "premium": 500.0, "currency": "MYR", "application_date": "2026-01-03T00:00:00Z", "next_step": "apply_coupon", "message": "Application submitted successfully"}, "status_code": 200, "execution_time_ms": 1, "error": null, "timestamp": "2026-01-07 18:28:55.989782"}, {"call_id": "call_sq4_20260107_182855_MV4_TOKIO_MARINE_COMPREHENSIVE_application_submit_staging", "execution_id": "sq4_20260107_182855_MV4_TOKIO_MARINE_COMPREHENSIVE", "tab_id": "sq4_20260107_182855_MV4_TOKIO_MARINE_COMPREHENSIVE", "api_step": "application_submit", "environment": "STAGING", "endpoint": "/api/v1/application-submit", "request_payload": {"category": "TOKIO", "product_id": "MARINE", "plan_id": "COMPREHENSIVE", "customer_data": {"customer_name": "John Doe", "customer_email": "john.doe@example.com", "customer_phone": "+60123456789", "date_of_birth": "1990-01-01", "address": {"street": "123 Main Street", "city": "Kuala Lumpur", "state": "Selangor", "postal_code": "50000", "country": "Malaysia"}}, "policy_start_date": "2026-02-01", "policy_end_date": "2027-01-31", "sum_insured": 50000, "application_date": "2026-01-07T18:28:55.992172"}, "response_data": {"status": "success", "application_id": "app_694f2f206b8c", "category": "TOKIO", "product_id": "MARINE", "plan_id": "COMPREHENSIVE", "premium": 500.0, "currency": "MYR", "application_date": "2026-01-03T00:00:00Z", "next_step": "apply_coupon", "message": "Application submitted successfully"}, "status_code": 200, "execution_time_ms": 0, "error": null, "timestamp": "2026-01-07 18:28:55.992172"}, {"call_id": "call_sq4_20260107_182855_MV4_TOKIO_MARINE_COMPREHENSIVE_apply_coupon_qa", "execution_id": "sq4_20260107_182855_MV4_TOKIO_MARINE_COMPREHENSIVE", "tab_id": "sq4_20260107_182855_MV4_TOKIO_MARINE_COMPREHENSIVE", "api_step": "apply_coupon", "environment": "QA", "endpoint": "/api/v1/apply-coupon", "request_payload": {"application_id": "app_b737fe7ca6be", "coupon_code": "SAVE10", "applied_at": "2026-01-07T18:28:56.045158"}, "response_data": {"status": "success", "application_id": "app_b737fe7ca6be", "coupon_code": "SAVE10", "discount_percent": 10, "original_amount": 500.0, "discount_amount": 50.0, "new_amount": 450.0, "currency": "MYR", "message": "Coupon applied successfully. You saved 10%!"}, "status_code": 200, "execution_time_ms": 0, "error": null, "timestamp": "2026-01-07 18:28:56.046153"}, {"call_id": "call_sq4_20260107_182855_MV4_TOKIO_MARINE_COMPREHENSIVE_apply_coupon_staging", "execution_id": "sq4_20260107_182855_MV4_TOKIO_MARINE_COMPREHENSIVE", "tab_id": "sq4_20260107_182855_MV4_TOKIO_MARINE_COMPREHENSIVE", "api_step": "apply_coupon", "environment": "STAGING", "endpoint": "/api/v1/apply-coupon", "request_payload": {"application_id": "app_b737fe7ca6be", "coupon_code": "SAVE10", "applied_at": "2026-01-07T18:28:56.051882"}, "response_data": {"status": "success", "application_id": "app_b737fe7ca6be", "coupon_code": "SAVE10", "discount_percent": 10, "original_amount": 500.0, "discount_amount": 50.0, "new_amount": 450.0, "currency": "MYR", "message": "Coupon applied successfully. You saved 10%!"}, "status_code": 200, "execution_time_ms": 0, "error": null, "timestamp": "2026-01-07 18:28:56.052881"}, {"call_id": "call_sq4_20260107_182855_MV4_TOKIO_MARINE_COMPREHENSIVE_payment_checkout_qa", "execution_id": "sq4_20260107_182855_MV4_TOKIO_MARINE_COMPREHENSIVE", "tab_id": "sq4_20260107_182855_MV4_TOKIO_MARINE_COMPREHENSIVE", "api_step": "payment_checkout", "environment": "QA", "endpoint": "/api/v1/payment-checkout", "request_payload": {"application_id": "app_b737fe7ca6be", "payment_method": "CREDIT_CARD", "payment_details": {"card_number": "4111111111111111", "card_holder": "JOHN DOE", "expiry_month": "12", "expiry_year": "2027", "cvv": "123"}, "amount": 500.0, "currency": "MYR", "checkout_date": "2026-01-07T18:28:56.060162"}, "response_data": {"status": "success", "application_id": "app_b737fe7ca6be", "payment_id": "pay_ee415af48305", "transaction_ref": "TXNB70E0325AD", "payment_method": "CREDIT_CARD", "amount": 450.0, "currency": "MYR", "payment_date": "2026-01-03T00:00:00Z", "payment_status": "completed", "policy_number": "POLAA75BE27", "message": "Payment processed successfully"}, "status_code": 200, "execution_time_ms": 0, "error": null, "timestamp": "2026-01-07 18:28:56.060162"}, {"call_id": "call_sq4_20260107_182855_MV4_TOKIO_MARINE_COMPREHENSIVE_payment_checkout_staging", "execution_id": "sq4_20260107_182855_MV4_TOKIO_MARINE_COMPREHENSIVE", "tab_id": "sq4_20260107_182855_MV4_TOKIO_MARINE_COMPREHENSIVE", "api_step": "payment_checkout", "environment": "STAGING", "endpoint": "/api/v1/payment-checkout", "request_payload": {"application_id": "app_b737fe7ca6be", "payment_method": "CREDIT_CARD", "payment_details": {"card_number": "4111111111111111", "card_holder": "JOHN DOE", "expiry_month": "12", "expiry_year": "2027", "cvv": "123"}, "amount": 500.0, "currency": "MYR", "checkout_date": "2026-01-07T18:28:56.087360"}, "response_data": {"status": "success", "application_id": "app_b737fe7ca6be", "payment_id": "pay_6627e9d2b283", "transaction_ref": "TXN5999AB0D20", "payment_method": "CREDIT_CARD", "amount": 450.0, "currency": "MYR", "payment_date": "2026-01-03T00:00:00Z", "payment_status": "completed", "policy_number": "POL3726C507", "message": "Payment processed successfully"}, "status_code": 200, "execution_time_ms": 0, "error": null, "timestamp": "2026-01-07 18:28:56.087360"}, {"call_id": "call_sq4_20260107_182855_MV4_TOKIO_MARINE_COMPREHENSIVE_admin_policy_list_qa", "execution_id": "sq4_20260107_182855_MV4_TOKIO_MARINE_COMPREHENSIVE", "tab_id": "sq4_20260107_182855_MV4_TOKIO_MARINE_COMPREHENSIVE", "api_step": "admin_policy_list", "environment": "QA", "endpoint": "/api/v1/admin-policy-list", "request_payload": {"admin_token": "", "filters": {}, "page": 1, "limit": 50}, "response_data": {"status": "success", "admin_token": "", "total_policies": 2, "page": 1, "limit": 50, "policies": [{"policy_id": "policy_56ac7685072a", "policy_number": "POL057CEED5", "customer_name": "John Doe", "category": "MV4", "product_id": "TOKIO_MARINE", "plan_id": "COMPREHENSIVE", "premium": 450.0, "policy_status": "active", "issue_date": "2026-01-03"}, {"policy_id": "policy_bd46edc92b21", "policy_number": "POL3B90A98F", "customer_name": "Jane Smith", "category": "TRAVEL", "product_id": "SOMPO", "plan_id": "TRAVEL_COMPREHENSIVE", "premium": 300.0, "policy_status": "active", "issue_date": "2026-01-02"}]}, "status_code": 200, "execution_time_ms": 0, "error": null, "timestamp": "2026-01-07 18:28:56.103884"}, {"call_id": "call_sq4_20260107_182855_MV4_TOKIO_MARINE_COMPREHENSIVE_admin_policy_list_staging", "execution_id": "sq4_20260107_182855_MV4_TOKIO_MARINE_COMPREHENSIVE", "tab_id": "sq4_20260107_182855_MV4_TOKIO_MARINE_COMPREHENSIVE", "api_step": "admin_policy_list", "environment": "STAGING", "endpoint": "/api/v1/admin-policy-list", "request_payload": {"admin_token": "", "filters": {}, "page": 1, "limit": 50}, "response_data": {"status": "success", "admin_token": "", "total_policies": 2, "page": 1, "limit": 50, "policies": [{"policy_id": "policy_48f317012163", "policy_number": "POLC89D384B", "customer_name": "John Doe", "category": "MV4", "product_id": "TOKIO_MARINE", "plan_id": "COMPREHENSIVE", "premium": 450.0, "policy_status": "active", "issue_date": "2026-01-03"}, {"policy_id": "policy_7422fb5666f6", "policy_number": "POL46D7212B", "customer_name": "Jane Smith", "category": "TRAVEL", "product_id": "SOMPO", "plan_id": "TRAVEL_COMPREHENSIVE", "premium": 300.0, "policy_status": "active", "issue_date": "2026-01-02"}]}, "status_code": 200, "execution_time_ms": 0, "error": null, "timestamp": "2026-01-07 18:28:56.108710"}, {"call_id": "call_sq4_20260107_182855_MV4_TOKIO_MARINE_COMPREHENSIVE_admin_policy_details_qa", "execution_id": "sq4_20260107_182855_MV4_TOKIO_MARINE_COMPREHENSIVE", "tab_id": "sq4_20260107_182855_MV4_TOKIO_MARINE_COMPREHENSIVE", "api_step": "admin_policy_details", "environment": "QA", "endpoint": "/api/v1/admin-policy-details", "request_payload": {"admin_token": "", "policy_id": "policy_12345"}, "response_data": {"status": "success", "policy_id": "policy_12345", "policy_number": "POLC5800FCE", "customer_name": "John Doe", "customer_email": "john.doe@example.com", "category": "MV4", "product_id": "TOKIO_MARINE", "plan_id": "COMPREHENSIVE", "premium": 450.0, "sum_insured": 50000.0, "currency": "MYR", "policy_status": "active", "coverage": {"vehicle_type": "Car", "vehicle_make": "Toyota", "vehicle_model": "Camry", "vehicle_year": "2022", "registration_number": "ABC1234"}, "benefits": ["Third Party Liability", "Own Damage", "Windscreen Coverage", "Legal Liability to Passengers"], "issue_date": "2026-01-03", "start_date": "2026-02-01", "end_date": "2027-01-31"}, "status_code": 200, "execution_time_ms": 0, "error": null, "timestamp": "2026-01-07 18:28:56.109691"}, {"call_id": "call_sq4_20260107_182855_MV4_TOKIO_MARINE_COMPREHENSIVE_admin_policy_details_staging", "execution_id": "sq4_20260107_182855_MV4_TOKIO_MARINE_COMPREHENSIVE", "tab_id": "sq4_20260107_182855_MV4_TOKIO_MARINE_COMPREHENSIVE", "api_step": "admin_policy_details", "environment": "STAGING", "endpoint": "/api/v1/admin-policy-details", "request_payload": {"admin_token": "", "policy_id": "policy_12345"}, "response_data": {"status": "success", "policy_id": "policy_12345", "policy_number": "POLF1613337", "customer_name": "John Doe", "customer_email": "john.doe@example.com", "category": "MV4", "product_id": "TOKIO_MARINE", "plan_id": "COMPREHENSIVE", "premium": 450.0, "sum_insured": 50000.0, "currency": "MYR", "policy_status": "active", "coverage": {"vehicle_type": "Car", "vehicle_make": "Toyota", "vehicle_model": "Camry", "vehicle_year": "2022", "registration_number": "ABC1234"}, "benefits": ["Third Party Liability", "Own Damage", "Windscreen Coverage", "Legal Liability to Passengers"], "issue_date": "2026-01-03", "start_date": "2026-02-01", "end_date": "2027-01-31"}, "status_code": 200, "execution_time_ms": 8, "error": null, "timestamp": "2026-01-07 18:28:56.118764"}, {"call_id": "call_sq4_20260107_182855_MV4_TOKIO_MARINE_COMPREHENSIVE_customer_policy_list_qa", "execution_id": "sq4_20260107_182855_MV4_TOKIO_MARINE_COMPREHENSIVE", "tab_id": "sq4_20260107_182855_MV4_TOKIO_MARINE_COMPREHENSIVE", "api_step": "customer_policy_list", "environment": "QA", "endpoint": "/api/v1/customer-policy-list", "request_payload": {"customer_token": "", "filters": {}, "page": 1, "limit": 50}, "response_data": {"status": "success", "customer_token": "", "total_policies": 1, "page": 1, "limit": 50, "policies": [{"policy_id": "policy_81c0695e9cf7", "policy_number": "POLE5B8D07C", "category": "MV4", "product_id": "TOKIO_MARINE", "plan_id": "COMPREHENSIVE", "premium": 450.0, "policy_status": "active", "renewal_date": "2027-01-31"}]}, "status_code": 200, "execution_time_ms": 0, "error": null, "timestamp": "2026-01-07 18:28:56.124661"}, {"call_id": "call_sq4_20260107_182855_MV4_TOKIO_MARINE_COMPREHENSIVE_customer_policy_list_staging", "execution_id": "sq4_20260107_182855_MV4_TOKIO_MARINE_COMPREHENSIVE", "tab_id": "sq4_20260107_182855_MV4_TOKIO_MARINE_COMPREHENSIVE", "api_step": "customer_policy_list", "environment": "STAGING", "endpoint": "/api/v1/customer-policy-list", "request_payload": {"customer_token": "", "filters": {}, "page": 1, "limit": 50}, "response_data": {"status": "success", "customer_token": "", "total_policies": 1, "page": 1, "limit": 50, "policies": [{"policy_id": "policy_08dcf95627fc", "policy_number": "POLCC634BA5", "category": "MV4", "product_id": "TOKIO_MARINE", "plan_id": "COMPREHENSIVE", "premium": 450.0, "policy_status": "active", "renewal_date": "2027-01-31"}]}, "status_code": 200, "execution_time_ms": 0, "error": null, "timestamp": "2026-01-07 18:28:56.133932"}, {"call_id": "call_sq4_20260107_182855_MV4_TOKIO_MARINE_COMPREHENSIVE_customer_policy_details_qa", "execution_id": "sq4_20260107_182855_MV4_TOKIO_MARINE_COMPREHENSIVE", "tab_id": "sq4_20260107_182855_MV4_TOKIO_MARINE_COMPREHENSIVE", "api_step": "customer_policy_details", "environment": "QA", "endpoint": "/api/v1/customer-policy-details", "request_payload": {"customer_token": "", "policy_id": "policy_12345"}, "response_data": {"status": "success", "policy_id": "policy_12345", "policy_number": "POL925B8CD2", "category": "MV4", "product_id": "TOKIO_MARINE", "plan_id": "COMPREHENSIVE", "premium": 450.0, "sum_insured": 50000.0, "currency": "MYR", "policy_status": "active", "start_date": "2026-02-01", "end_date": "2027-01-31", "benefits": ["Third Party Liability", "Own Damage", "Windscreen Coverage", "Legal Liability to Passengers"], "exclusions": ["Driving under influence", "Unauthorized driver", "Racing competitions"], "contact_support": {"phone": "+601800123456", "email": "support@insurance.com", "hours": "24/7"}}, "status_code": 200, "execution_time_ms": 0, "error": null, "timestamp": "2026-01-07 18:28:56.134930"}, {"call_id": "call_sq4_20260107_182855_MV4_TOKIO_MARINE_COMPREHENSIVE_customer_policy_details_staging", "execution_id": "sq4_20260107_182855_MV4_TOKIO_MARINE_COMPREHENSIVE", "tab_id": "sq4_20260107_182855_MV4_TOKIO_MARINE_COMPREHENSIVE", "api_step": "customer_policy_details", "environment": "STAGING", "endpoint": "/api/v1/customer-policy-details", "request_payload": {"customer_token": "", "policy_id": "policy_12345"}, "response_data": {"status": "success", "policy_id": "policy_12345", "policy_number": "POLBECD9219", "category": "MV4", "product_id": "TOKIO_MARINE", "plan_id": "COMPREHENSIVE", "premium": 450.0, "sum_insured": 50000.0, "currency": "MYR", "policy_status": "active", "start_date": "2026-02-01", "end_date": "2027-01-31", "benefits": ["Third Party Liability", "Own Damage", "Windscreen Coverage", "Legal Liability to Passengers"], "exclusions": ["Driving under influence", "Unauthorized driver", "Racing competitions"], "contact_support": {"phone": "+601800123456", "email": "support@insurance.com", "hours": "24/7"}}, "status_code": 200, "execution_time_ms": 0, "error": null, "timestamp": "2026-01-07 18:28:56.134930"}], "comparisons": [{"comparison_id": "cmp_sq4_20260107_182855_MV4_TOKIO_MARINE_COMPREHENSIVE_application_submit", "execution_id": "sq4_20260107_182855_MV4_TOKIO_MARINE_COMPREHENSIVE", "timestamp": "2026-01-07 18:28:56.186981", "api_step": "application_submit", "target_environment": "QA", "staging_environment": "STAGING", "target_response": {"status": "success", "application_id": "app_b737fe7ca6be", "category": "TOKIO", "product_id": "MARINE", "plan_id": "COMPREHENSIVE", "premium": 500.0, "currency": "MYR", "application_date": "2026-01-03T00:00:00Z", "next_step": "apply_coupon", "message": "Application submitted successfully"}, "staging_response": {"status": "success", "application_id": "app_694f2f206b8c", "category": "TOKIO", "product_id": "MARINE", "plan_id": "COMPREHENSIVE", "premium": 500.0, "currency": "MYR", "application_date": "2026-01-03T00:00:00Z", "next_step": "apply_coupon", "message": "Application submitted successfully"}, "differences": [{"field_path": "application_id", "target_value": "app_b737fe7ca6be", "staging_value": "app_694f2f206b8c", "severity": "info", "description": "Value differs for 'application_id': target=app_b737fe7ca6be, staging=app_694f2f206b8c"}], "summary": {"critical": 0, "warning": 0, "info": 1, "total": 1}}, {"comparison_id": "cmp_sq4_20260107_182855_MV4_TOKIO_MARINE_COMPREHENSIVE_apply_coupon", "execution_id": "sq4_20260107_182855_MV4_TOKIO_MARINE_COMPREHENSIVE", "timestamp": "2026-01-07 18:28:56.186981", "api_step": "apply_coupon", "target_environment": "QA", "staging_environment": "STAGING", "target_response": {"status": "success", "application_id": "app_b737fe7ca6be", "coupon_code": "SAVE10", "discount_percent": 10, "original_amount": 500.0, "discount_amount": 50.0, "new_amount": 450.0, "currency": "MYR", "message": "Coupon applied successfully. You saved 10%!"}, "staging_response": {"status": "success", "application_id": "app_b737fe7ca6be", "coupon_code": "SAVE10", "discount_percent": 10, "original_amount": 500.0, "discount_amount": 50.0, "new_amount": 450.0, "currency": "MYR", "message": "Coupon applied successfully. You saved 10%!"}, "differences": [], "summary": {"critical": 0, "warning": 0, "info": 0, "total": 0}}, {"comparison_id": "cmp_sq4_20260107_182855_MV4_TOKIO_MARINE_COMPREHENSIVE_payment_checkout", "execution_id": "sq4_20260107_182855_MV4_TOKIO_MARINE_COMPREHENSIVE", "timestamp": "2026-01-07 18:28:56.206704", "api_step": "payment_checkout", "target_environment": "QA", "staging_environment": "STAGING", "target_response": {"status": "success", "application_id": "app_b737fe7ca6be", "payment_id": "pay_ee415af48305", "transaction_ref": "TXNB70E0325AD", "payment_method": "CREDIT_CARD", "amount": 450.0, "currency": "MYR", "payment_date": "2026-01-03T00:00:00Z", "payment_status": "completed", "policy_number": "POLAA75BE27", "message": "Payment processed successfully"}, "staging_response": {"status": "success", "application_id": "app_b737fe7ca6be", "payment_id": "pay_6627e9d2b283", "transaction_ref": "TXN5999AB0D20", "payment_method": "CREDIT_CARD", "amount": 450.0, "currency": "MYR", "payment_date": "2026-01-03T00:00:00Z", "payment_status": "completed", "policy_number": "POL3726C507", "message": "Payment processed successfully"}, "differences": [{"field_path": "transaction_ref", "target_value": "TXNB70E0325AD", "staging_value": "TXN5999AB0D20", "severity": "info", "description": "Value differs for 'transaction_ref': target=TXNB70E0325AD, staging=TXN5999AB0D20"}, {"field_path": "policy_number", "target_value": "POLAA75BE27", "staging_value": "POL3726C507", "severity": "critical", "description": "Value differs for 'policy_number': target=POLAA75BE27, staging=POL3726C507"}, {"field_path": "payment_id", "target_value": "pay_ee415af48305", "staging_value": "pay_6627e9d2b283", "severity": "info", "description": "Value differs for 'payment_id': target=pay_ee415af48305, staging=pay_6627e9d2b283"}], "summary": {"critical": 1, "warning": 0, "info": 2, "total": 3}}, {"comparison_id": "cmp_sq4_20260107_182855_MV4_TOKIO_MARINE_COMPREHENSIVE_admin_policy_list", "execution_id": "sq4_20260107_182855_MV4_TOKIO_MARINE_COMPREHENSIVE", "timestamp": "2026-01-07 18:28:56.206704", "api_step": "admin_policy_list", "target_environment": "QA", "staging_environment": "STAGING", "target_response": {"status": "success", "admin_token": "", "total_policies": 2, "page": 1, "limit": 50, "policies": [{"policy_id": "policy_56ac7685072a", "policy_number": "POL057CEED5", "customer_name": "John Doe", "category": "MV4", "product_id": "TOKIO_MARINE", "plan_id": "COMPREHENSIVE", "premium": 450.0, "policy_status": "active", "issue_date": "2026-01-03"}, {"policy_id": "policy_bd46edc92b21", "policy_number": "POL3B90A98F", "customer_name": "Jane Smith", "category": "TRAVEL", "product_id": "SOMPO", "plan_id": "TRAVEL_COMPREHENSIVE", "premium": 300.0, "policy_status": "active", "issue_date": "2026-01-02"}]}, "staging_response": {"status": "success", "admin_token": "", "total_policies": 2, "page": 1, "limit": 50, "policies": [{"policy_id": "policy_48f317012163", "policy_number": "POLC89D384B", "customer_name": "John Doe", "category": "MV4", "product_id": "TOKIO_MARINE", "plan_id": "COMPREHENSIVE", "premium": 450.0, "policy_status": "active", "issue_date": "2026-01-03"}, {"policy_id": "policy_7422fb5666f6", "policy_number": "POL46D7212B", "customer_name": "Jane Smith", "category": "TRAVEL", "product_id": "SOMPO", "plan_id": "TRAVEL_COMPREHENSIVE", "premium": 300.0, "policy_status": "active", "issue_date": "2026-01-02"}]}, "differences": [{"field_path": "policies", "target_value": [{"policy_id": "policy_56ac7685072a", "policy_number": "POL057CEED5", "customer_name": "John Doe", "category": "MV4", "product_id": "TOKIO_MARINE", "plan_id": "COMPREHENSIVE", "premium": 450.0, "policy_status": "active"}, {"policy_id": "policy_bd46edc92b21", "policy_number": "POL3B90A98F", "customer_name": "Jane Smith", "category": "TRAVEL", "product_id": "SOMPO", "plan_id": "TRAVEL_COMPREHENSIVE", "premium": 300.0, "policy_status": "active"}], "staging_value": [{"policy_id": "policy_48f317012163", "policy_number": "POLC89D384B", "customer_name": "John Doe", "category": "MV4", "product_id": "TOKIO_MARINE", "plan_id": "COMPREHENSIVE", "premium": 450.0, "policy_status": "active"}, {"policy_id": "policy_7422fb5666f6", "policy_number": "POL46D7212B", "customer_name": "Jane Smith", "category": "TRAVEL", "product_id": "SOMPO", "plan_id": "TRAVEL_COMPREHENSIVE", "premium": 300.0, "policy_status": "active"}], "severity": "info", "description": "Value differs for 'policies': target=[{'policy_id': 'policy_56ac7685072a', 'policy_number': 'POL057CEED5', 'customer_name': 'John Doe', 'category': 'MV4', 'product_id': 'TOKIO_MARINE', 'plan_id': 'COMPREHENSIVE', 'premium': 450.0, 'policy_status': 'active'}, {'policy_id': 'policy_bd46edc92b21', 'policy_number': 'POL3B90A98F', 'customer_name': 'Jane Smith', 'category': 'TRAVEL', 'product_id': 'SOMPO', 'plan_id': 'TRAVEL_COMPREHENSIVE', 'premium': 300.0, 'policy_status': 'active'}], staging=[{'policy_id': 'policy_48f317012163', 'policy_number': 'POLC89D384B', 'customer_name': 'John Doe', 'category': 'MV4', 'product_id': 'TOKIO_MARINE', 'plan_id': 'COMPREHENSIVE', 'premium': 450.0, 'policy_status': 'active'}, {'policy_id': 'policy_7422fb5666f6', 'policy_number': 'POL46D7212B', 'customer_name': 'Jane Smith', 'category': 'TRAVEL', 'product_id': 'SOMPO', 'plan_id': 'TRAVEL_COMPREHENSIVE', 'premium': 300.0, 'policy_status': 'active'}]"}], "summary": {"critical": 0, "warning": 0, "info": 1, "total": 1}}, {"comparison_id": "cmp_sq4_20260107_182855_MV4_TOKIO_MARINE_COMPREHENSIVE_admin_policy_details", "execution_id": "sq4_20260107_182855_MV4_TOKIO_MARINE_COMPREHENSIVE", "timestamp": "2026-01-07 18:28:56.225686", "api_step": "admin_policy_details", "target_environment": "QA", "staging_environment": "STAGING", "target_response": {"status": "success", "policy_id": "policy_12345", "policy_number": "POLC5800FCE", "customer_name": "John Doe", "customer_email": "john.doe@example.com", "category": "MV4", "product_id": "TOKIO_MARINE", "plan_id": "COMPREHENSIVE", "premium": 450.0, "sum_insured": 50000.0, "currency": "MYR", "policy_status": "active", "coverage": {"vehicle_type": "Car", "vehicle_make": "Toyota", "vehicle_model": "Camry", "vehicle_year": "2022", "registration_number": "ABC1234"}, "benefits": ["Third Party Liability", "Own Damage", "Windscreen Coverage", "Legal Liability to Passengers"], "issue_date": "2026-01-03", "start_date": "2026-02-01", "end_date": "2027-01-31"}, "staging_response": {"status": "success", "policy_id": "policy_12345", "policy_number": "POLF1613337", "customer_name": "John Doe", "customer_email": "john.doe@example.com", "category": "MV4", "product_id": "TOKIO_MARINE", "plan_id": "COMPREHENSIVE", "premium": 450.0, "sum_insured": 50000.0, "currency": "MYR", "policy_status": "active", "coverage": {"vehicle_type": "Car", "vehicle_make": "Toyota", "vehicle_model": "Camry", "vehicle_year": "2022", "registration_number": "ABC1234"}, "benefits": ["Third Party Liability", "Own Damage", "Windscreen Coverage", "Legal Liability to Passengers"], "issue_date": "2026-01-03", "start_date": "2026-02-01", "end_date": "2027-01-31"}, "differences": [{"field_path": "policy_number", "target_value": "POLC5800FCE", "staging_value": "POLF1613337", "severity": "critical", "description": "Value differs for 'policy_number': target=POLC5800FCE, staging=POLF1613337"}], "summary": {"critical": 1, "warning": 0, "info": 0, "total": 1}}, {"comparison_id": "cmp_sq4_20260107_182855_MV4_TOKIO_MARINE_COMPREHENSIVE_customer_policy_list", "execution_id": "sq4_20260107_182855_MV4_TOKIO_MARINE_COMPREHENSIVE", "timestamp": "2026-01-07 18:28:56.226922", "api_step": "customer_policy_list", "target_environment": "QA", "staging_environment": "STAGING", "target_response": {"status": "success", "customer_token": "", "total_policies": 1, "page": 1, "limit": 50, "policies": [{"policy_id": "policy_81c0695e9cf7", "policy_number": "POLE5B8D07C", "category": "MV4", "product_id": "TOKIO_MARINE", "plan_id": "COMPREHENSIVE", "premium": 450.0, "policy_status": "active", "renewal_date": "2027-01-31"}]}, "staging_response": {"status": "success", "customer_token": "", "total_policies": 1, "page": 1, "limit": 50, "policies": [{"policy_id": "policy_08dcf95627fc", "policy_number": "POLCC634BA5", "category": "MV4", "product_id": "TOKIO_MARINE", "plan_id": "COMPREHENSIVE", "premium": 450.0, "policy_status": "active", "renewal_date": "2027-01-31"}]}, "differences": [{"field_path": "policies", "target_value": [{"policy_id": "policy_81c0695e9cf7", "policy_number": "POLE5B8D07C", "category": "MV4", "product_id": "TOKIO_MARINE", "plan_id": "COMPREHENSIVE", "premium": 450.0, "policy_status": "active"}], "staging_value": [{"policy_id": "policy_08dcf95627fc", "policy_number": "POLCC634BA5", "category": "MV4", "product_id": "TOKIO_MARINE", "plan_id": "COMPREHENSIVE", "premium": 450.0, "policy_status": "active"}], "severity": "info", "description": "Value differs for 'policies': target=[{'policy_id': 'policy_81c0695e9cf7', 'policy_number': 'POLE5B8D07C', 'category': 'MV4', 'product_id': 'TOKIO_MARINE', 'plan_id': 'COMPREHENSIVE', 'premium': 450.0, 'policy_status': 'active'}], staging=[{'policy_id': 'policy_08dcf95627fc', 'policy_number': 'POLCC634BA5', 'category': 'MV4', 'product_id': 'TOKIO_MARINE', 'plan_id': 'COMPREHENSIVE', 'premium': 450.0, 'policy_status': 'active'}]"}], "summary": {"critical": 0, "warning": 0, "info": 1, "total": 1}}, {"comparison_id": "cmp_sq4_20260107_182855_MV4_TOKIO_MARINE_COMPREHENSIVE_customer_policy_details", "execution_id": "sq4_20260107_182855_MV4_TOKIO_MARINE_COMPREHENSIVE", "timestamp": "2026-01-07 18:28:56.242232", "api_step": "customer_policy_details", "target_environment": "QA", "staging_environment": "STAGING", "target_response": {"status": "success", "policy_id": "policy_12345", "policy_number": "POL925B8CD2", "category": "MV4", "product_id": "TOKIO_MARINE", "plan_id": "COMPREHENSIVE", "premium": 450.0, "sum_insured": 50000.0, "currency": "MYR", "policy_status": "active", "start_date": "2026-02-01", "end_date": "2027-01-31", "benefits": ["Third Party Liability", "Own Damage", "Windscreen Coverage", "Legal Liability to Passengers"], "exclusions": ["Driving under influence", "Unauthorized driver", "Racing competitions"], "contact_support": {"phone": "+601800123456", "email": "support@insurance.com", "hours": "24/7"}}, "staging_response": {"status": "success", "policy_id": "policy_12345", "policy_number": "POLBECD9219", "category": "MV4", "product_id": "TOKIO_MARINE", "plan_id": "COMPREHENSIVE", "premium": 450.0, "sum_insured": 50000.0, "currency": "MYR", "policy_status": "active", "start_date": "2026-02-01", "end_date": "2027-01-31", "benefits": ["Third Party Liability", "Own Damage", "Windscreen Coverage", "Legal Liability to Passengers"], "exclusions": ["Driving under influence", "Unauthorized driver", "Racing competitions"], "contact_support": {"phone": "+601800123456", "email": "support@insurance.com", "hours": "24/7"}}, "differences": [{"field_path": "policy_number", "target_value": "POL925B8CD2", "staging_value": "POLBECD9219", "severity": "critical", "description": "Value differs for 'policy_number': target=POL925B8CD2, staging=POLBECD9219"}], "summary": {"critical": 1, "warning": 0, "info": 0, "total": 1}}], "reports": {"execution_id": "sq4_20260107_182855_MV4_TOKIO_MARINE_COMPREHENSIVE", "status": "completed", "total_api_calls": 14, "failed_api_calls": 0, "summary": "Execution completed"}, "has_failures": false}